exampy/__init__.py
exampy/_math.py
exampy/integrate/__init__.py
exampy/integrate/_integrate.py
exampy-0.2.dist-info/LICENSE
exampy-0.2.dist-info/METADATA
exampy-0.2.dist-info/WHEEL
exampy-0.2.dist-info/top_level.txt
exampy-0.2.dist-info/RECORD
