Metadata-Version: 2.1
Name: exampy
Version: 0.2
Summary: A small example Python package
Home-page: UNKNOWN
Author: Jo Bovy
Author-email: bovy@astro.utoronto.ca
License: UNKNOWN
Platform: UNKNOWN
Requires-Dist: numpy
